setup.py
distribution_forLearningPyPi_142857_285714_571428/Binomialdistribution.py
distribution_forLearningPyPi_142857_285714_571428/Gaussiandistribution.py
distribution_forLearningPyPi_142857_285714_571428/Generaldistribution.py
distribution_forLearningPyPi_142857_285714_571428/__init__.py
distribution_forLearningPyPi_142857_285714_571428.egg-info/PKG-INFO
distribution_forLearningPyPi_142857_285714_571428.egg-info/SOURCES.txt
distribution_forLearningPyPi_142857_285714_571428.egg-info/dependency_links.txt
distribution_forLearningPyPi_142857_285714_571428.egg-info/not-zip-safe
distribution_forLearningPyPi_142857_285714_571428.egg-info/top_level.txt