Metadata-Version: 1.0
Name: distribution-forLearningPyPi-142857-285714-571428
Version: 0.1
Summary: Gaussian & Binomial distribution distributions
Home-page: UNKNOWN
Author: UNKNOWN
Author-email: UNKNOWN
License: UNKNOWN
Platform: UNKNOWN
